README.txt
setup.py
collective/__init__.py
collective.sharingroles.egg-info/PKG-INFO
collective.sharingroles.egg-info/SOURCES.txt
collective.sharingroles.egg-info/dependency_links.txt
collective.sharingroles.egg-info/entry_points.txt
collective.sharingroles.egg-info/namespace_packages.txt
collective.sharingroles.egg-info/not-zip-safe
collective.sharingroles.egg-info/requires.txt
collective.sharingroles.egg-info/top_level.txt
collective/sharingroles/__init__.py
collective/sharingroles/configure.zcml
collective/sharingroles/exportimport.py
collective/sharingroles/role.py
collective/sharingroles/tests.py
docs/HISTORY.txt
docs/INSTALL.txt
docs/LICENSE.GPL
docs/LICENSE.txt