Metadata-Version: 1.0
Name: collective.sharingroles
Version: 1.0b2
Summary: Makes it easier to manage the roles that show up on the 'sharing' page in Plone 3
Home-page: http://pypi.python.org/pypi/collective.sharingroles
Author: Martin Aspeli
Author-email: optilude@gmail.com
License: GPL
Keywords: plone sharing local roles
Platform: UNKNOWN
Classifier: Framework :: Plone
Classifier: Programming Language :: Python
Classifier: Topic :: Software Development :: Libraries :: Python Modules
